{
 "date": "2026-07-12",
 "updatedAt": "2026-07-12 13:42",
 "stocks": [
  {
   "name": "上证指数",
   "value": "3996.16",
   "change": "-40.43",
   "pct": "-1.00%"
  },
  {
   "name": "深证成指",
   "value": "15046.67",
   "change": "-352.06",
   "pct": "-2.29%"
  },
  {
   "name": "创业板指",
   "value": "3842.73",
   "change": "-175.44",
   "pct": "-4.37%"
  }
 ],
 "gold": {
  "name": "黄金·伦敦金",
  "value": "4119.01",
  "unit": "美元/盎司"
 },
 "forex": [
  {
   "name": "美元",
   "value": "6.790"
  },
  {
   "name": "欧元",
   "value": "7.753"
  },
  {
   "name": "港币",
   "value": "0.866"
  },
  {
   "name": "100日元",
   "value": "4.193"
  }
 ],
 "btc": {
  "usd": "64,009",
  "cny": "433,819",
  "pct": "-0.26%"
 },
 "weibo": [
  {
   "title": "中华人民共和国外交部郑重声明",
   "link": "https://s.weibo.com/weibo?q=%E4%B8%AD%E5%8D%8E%E4%BA%BA%E6%B0%91%E5%85%B1%E5%92%8C%E5%9B%BD%E5%A4%96%E4%BA%A4%E9%83%A8%E9%83%91%E9%87%8D%E5%A3%B0%E6%98%8E"
  },
  {
   "title": "英格兰派出了贝林哄哈兰德",
   "link": "https://s.weibo.com/weibo?q=%E8%8B%B1%E6%A0%BC%E5%85%B0%E6%B4%BE%E5%87%BA%E4%BA%86%E8%B4%9D%E6%9E%97%E5%93%84%E5%93%88%E5%85%B0%E5%BE%B7"
  },
  {
   "title": "国产动力舟桥抗洪有多硬核",
   "link": "https://s.weibo.com/weibo?q=%E5%9B%BD%E4%BA%A7%E5%8A%A8%E5%8A%9B%E8%88%9F%E6%A1%A5%E6%8A%97%E6%B4%AA%E6%9C%89%E5%A4%9A%E7%A1%AC%E6%A0%B8"
  },
  {
   "title": "火鸡面被台风孤立了",
   "link": "https://s.weibo.com/weibo?q=%E7%81%AB%E9%B8%A1%E9%9D%A2%E8%A2%AB%E5%8F%B0%E9%A3%8E%E5%AD%A4%E7%AB%8B%E4%BA%86"
  },
  {
   "title": "BLG 失望",
   "link": "https://s.weibo.com/weibo?q=BLG%20%E5%A4%B1%E6%9C%9B"
  },
  {
   "title": "功夫女足豆瓣6.6票房却杀疯了",
   "link": "https://s.weibo.com/weibo?q=%E5%8A%9F%E5%A4%AB%E5%A5%B3%E8%B6%B3%E8%B1%86%E7%93%A36.6%E7%A5%A8%E6%88%BF%E5%8D%B4%E6%9D%80%E7%96%AF%E4%BA%86"
  },
  {
   "title": "一直以为取卡针的作用只有换电话卡",
   "link": "https://s.weibo.com/weibo?q=%E4%B8%80%E7%9B%B4%E4%BB%A5%E4%B8%BA%E5%8F%96%E5%8D%A1%E9%92%88%E7%9A%84%E4%BD%9C%E7%94%A8%E5%8F%AA%E6%9C%89%E6%8D%A2%E7%94%B5%E8%AF%9D%E5%8D%A1"
  },
  {
   "title": "汪苏泷原本打算开30分钟后退票",
   "link": "https://s.weibo.com/weibo?q=%E6%B1%AA%E8%8B%8F%E6%B3%B7%E5%8E%9F%E6%9C%AC%E6%89%93%E7%AE%97%E5%BC%8030%E5%88%86%E9%92%9F%E5%90%8E%E9%80%80%E7%A5%A8"
  },
  {
   "title": "百花杀",
   "link": "https://s.weibo.com/weibo?q=%E7%99%BE%E8%8A%B1%E6%9D%80"
  },
  {
   "title": "赛力斯预计半年净亏损15至18亿元",
   "link": "https://s.weibo.com/weibo?q=%E8%B5%9B%E5%8A%9B%E6%96%AF%E9%A2%84%E8%AE%A1%E5%8D%8A%E5%B9%B4%E5%87%80%E4%BA%8F%E6%8D%9F15%E8%87%B318%E4%BA%BF%E5%85%83"
  },
  {
   "title": "季节说誓约打胎",
   "link": "https://s.weibo.com/weibo?q=%E5%AD%A3%E8%8A%82%E8%AF%B4%E8%AA%93%E7%BA%A6%E6%89%93%E8%83%8E"
  },
  {
   "title": "山东也要迎战台风了",
   "link": "https://s.weibo.com/weibo?q=%E5%B1%B1%E4%B8%9C%E4%B9%9F%E8%A6%81%E8%BF%8E%E6%88%98%E5%8F%B0%E9%A3%8E%E4%BA%86"
  }
 ],
 "zhihu": [
  {
   "title": "如何看待瑞士前锋恩博洛偷鸡不成蚀把米，假摔骗黄未遂，VAR回放后反被裁判罚下，离场时抱头痛哭？",
   "link": "https://www.zhihu.com/question/2059586957143795316"
  },
  {
   "title": "世界杯四强法国、阿根廷、西班牙、英格兰，正好是 FIFA 排名前四的球队，你更看好谁夺冠？",
   "link": "https://www.zhihu.com/question/2059606032012113468"
  },
  {
   "title": "为什么台风预报的时候来势汹汹，但真登陆了感觉没有那么强烈？",
   "link": "https://www.zhihu.com/question/1943291837109478434"
  },
  {
   "title": "将飞机票和火车票的时间显示改为30小时制，是否能有效防止凌晨出发的旅客因时间理解问题而迟到24小时？",
   "link": "https://www.zhihu.com/question/2015414302245422985"
  },
  {
   "title": "小红书前员工再发文实名举报 IPO 合规，哪些信息值得关注？",
   "link": "https://www.zhihu.com/question/2058623048639689021"
  },
  {
   "title": "如何看待中华人民共和国外交部发布关于有关国家炒作「南海仲裁案裁决」出台十年的声明？释放了哪些信号？",
   "link": "https://www.zhihu.com/question/2059717066660303002"
  },
  {
   "title": "如何看待 7 月 12 日伊朗再次宣布关闭霍尔木兹海峡？这种封锁会成为常态吗？从长期看，要怎么应对？",
   "link": "https://www.zhihu.com/question/2059566718733776028"
  },
  {
   "title": "哈兰德以5场比赛7个进球告别本届世界杯，这一成绩如何？他给你留下哪些令人印象深刻的瞬间？",
   "link": "https://www.zhihu.com/question/2059562876868583536"
  },
  {
   "title": "特厨隋坡探店全差评餐厅引争议，老板「逆天回怼」是高明还是失策？",
   "link": "https://www.zhihu.com/question/2059021609504186485"
  },
  {
   "title": "孙悟空打死六耳猕猴后变得顺从乖巧，再也没被念紧箍咒，原因是什么？",
   "link": "https://www.zhihu.com/question/2055315080015828549"
  },
  {
   "title": "2026 MSI 总决赛 HLE 3:2 复仇 BLG 夺得冠军，如何评价这场比赛？",
   "link": "https://www.zhihu.com/question/2059612028357063761"
  },
  {
   "title": "盛唐时期大部分唐朝人真的能每天以肉饼为食吗？",
   "link": "https://www.zhihu.com/question/1920148899752023682"
  }
 ]
}